{
  "user": [
    {
      "id": "1",
      "name": "parkhyunsung",
      "email": "rlatnsskd123@gmail.com"
    },
    {
      "id": "2",
      "name": "kimjungah",
      "email": "jjongr1993@gmail.com"
    },
    {
      "id": "3",
      "name": "박현성",
      "email": "rlatnsskd123@gmail.com"
    },
    {
      "id": "4",
      "name": "김정아",
      "email": "jjongr@gmail.com"
    },
    {
      "id": "",
      "name": "",
      "email": ""
    },
    {
      "id": "6",
      "name": "park",
      "email": "park@gmail.com"
    },
    {
      "id": "435",
      "name": "안녕",
      "email": "rlatns@naver.com"
    },
    {
      "id": "55",
      "name": "정아사룽",
      "email": "rlatn@naver.com"
    }
  ]
}